[{"cid":"4960","cname":"Eye Cream & Serum(眼霜和精华素)","cnameCn":"眼霜和精华素","isLeaf":1,"leaf":true,"level":3,"pL1Id":"129","pL1Name":"Health & Beauty(健康与美容)","pL2Id":"2448","pL2Name":"Eye Care(眼睛护理)"},{"cid":"9662","cname":"Eye Mask(眼罩)","cnameCn":"眼罩","isLeaf":1,"leaf":true,"level":3,"pL1Id":"129","pL1Name":"Health & Beauty(健康与美容)","pL2Id":"2448","pL2Name":"Eye Care(眼睛护理)"},{"cid":"9663","cname":"Prescription Lens & Care(处方镜片和护理)","cnameCn":"处方镜片和护理","isLeaf":1,"leaf":true,"level":3,"pL1Id":"129","pL1Name":"Health & Beauty(健康与美容)","pL2Id":"2448","pL2Name":"Eye Care(眼睛护理)"},{"cid":"9664","cname":"Others(其他)","cnameCn":"其他","isLeaf":1,"leaf":true,"level":3,"pL1Id":"129","pL1Name":"Health & Beauty(健康与美容)","pL2Id":"2448","pL2Name":"Eye Care(眼睛护理)"}]