[{"cid":"15281","cname":"其他","isLeaf":1,"leaf":true,"level":3,"pL1Id":"10076","pL1Name":"汽機車零件百貨","pL2Id":"15280","pL2Name":"汽車"},{"cid":"15282","cname":"四門房車、掀背車","isLeaf":1,"leaf":true,"level":3,"pL1Id":"10076","pL1Name":"汽機車零件百貨","pL2Id":"15280","pL2Name":"汽車"},{"cid":"15283","cname":"雙門跑車、敞篷車","isLeaf":1,"leaf":true,"level":3,"pL1Id":"10076","pL1Name":"汽機車零件百貨","pL2Id":"15280","pL2Name":"汽車"},{"cid":"15284","cname":"休旅車","isLeaf":1,"leaf":true,"level":3,"pL1Id":"10076","pL1Name":"汽機車零件百貨","pL2Id":"15280","pL2Name":"汽車"},{"cid":"15285","cname":"商用車、貨車","isLeaf":1,"leaf":true,"level":3,"pL1Id":"10076","pL1Name":"汽機車零件百貨","pL2Id":"15280","pL2Name":"汽車"}]