[{"cid":"11794","cname":"Plimsolls(橡胶底帆布鞋)","cnameCn":"橡胶底帆布鞋","isLeaf":1,"leaf":true,"level":3,"pL1Id":"2593","pL1Name":"Men's Shoes(男装鞋)","pL2Id":"2595","pL2Name":"Sneakers(球鞋)"},{"cid":"4857","cname":"Others(其他)","cnameCn":"其他","isLeaf":1,"leaf":true,"level":3,"pL1Id":"2593","pL1Name":"Men's Shoes(男装鞋)","pL2Id":"2595","pL2Name":"Sneakers(球鞋)"},{"cid":"7135","cname":"High Tops(高帮)","cnameCn":"高帮","isLeaf":1,"leaf":true,"level":3,"pL1Id":"2593","pL1Name":"Men's Shoes(男装鞋)","pL2Id":"2595","pL2Name":"Sneakers(球鞋)"},{"cid":"7136","cname":"Low Tops(低帮)","cnameCn":"低帮","isLeaf":1,"leaf":true,"level":3,"pL1Id":"2593","pL1Name":"Men's Shoes(男装鞋)","pL2Id":"2595","pL2Name":"Sneakers(球鞋)"}]